pygdmUI/__init__.py
pygdmUI/custom_qt_objects.py
pygdmUI/main.py
pygdmUI/pygdm_function_configs.py
pygdmUI/qt_ui_base.py
pygdmUI-0.1.dist-info/LICENSE.txt
pygdmUI-0.1.dist-info/METADATA
pygdmUI-0.1.dist-info/WHEEL
pygdmUI-0.1.dist-info/top_level.txt
pygdmUI-0.1.dist-info/RECORD
