Metadata-Version: 2.1
Name: pygdmUI
Version: 0.1
Summary: A python full-field electrodynamical solver, based on the Green dyadic method (volume integral technique in frequency domain).
Home-page: https://gitlab.com/wiechapeter/pygdm-ui
Author: Peter R. Wiecha
Author-email: pwiecha@laas.fr
License: GPLv3+
Keywords: coupled dipoles method,green dyadic method,electrodynamical simulations,nano optics,frequency-domain
Platform: UNKNOWN
Classifier: Development Status :: 5 - Production/Stable
Classifier: Topic :: Scientific/Engineering :: Physics
Classifier: Environment :: Console
Classifier: Programming Language :: Python :: 3.5
Classifier: Programming Language :: Python :: 3.6
Classifier: Programming Language :: Python :: 3.7
Classifier: License :: OSI Approved :: GNU General Public License v3 or later (GPLv3+)
Classifier: Intended Audience :: Science/Research
Requires-Python: >=3.5
Requires-Dist: pyGDM2
Requires-Dist: numpy
Requires-Dist: mayavi
Requires-Dist: matplotlib
Requires-Dist: pyQt5
